[{"title": "Movenpick Resort & Marine Spa Sousse", "note": "3 196 avis", "address": "Boulevard du 14 Janvier, Sousse, Gouvernorat de Sousse, Tunisie"}, {"title": "Thalassa Sousse Resort & Aquapark", "note": "1 554 avis", "address": "2011 Boulevard 14 Janvier, Sousse, Gouvernorat de Sousse, Tunisie"}, {"title": "Riadh Palms Hotel", "note": "3 845 avis", "address": "Avenue du 14 Janvier, Sousse, Gouvernorat de Sousse, Tunisie"}, {"title": "Sousse Palace", "note": "212 avis", "address": "30 Avenue Habib Bourguiba, Sousse, Gouvernorat de Sousse, Tunisie"}, {"title": "Marhaba Royal Salem", "note": "2 511 avis", "address": "Boulevard 14 Janvier, Sousse, Gouvernorat de Sousse, Tunisie"}, {"title": "El Ksar Resort & Thalasso", "note": "1 559 avis", "address": "14 Boulevard, Sousse, Gouvernorat de Sousse, Tunisie"}, {"title": "marhaba beach", "note": "3 233 avis", "address": "Boulevard 14 Janvier, Sousse, Gouvernorat de Sousse, Tunisie"}, {"title": "Iberostar Selection Diar El Andalous", "note": "2 637 avis", "address": "B.P. 40, Port El Kantaoui, Port El Kantaoui, Gouvernorat de Sousse, Tunisie"}, {"title": "El Mouradi Palm Marina", "note": "2 177 avis", "address": "Zone Touristique, Port El Kantaoui, Gouvernorat de Sousse, Tunisie"}, {"title": "Seabel Alhambra Beach Golf & Spa", "note": "2 392 avis", "address": "Bp 16, Port El Kantaoui, Gouvernorat de Sousse, Tunisie"}, {"title": "Marhaba Salem", "note": "1 897 avis", "address": "Boulevard 14 Janvier, Sousse, Gouvernorat de Sousse, Tunisie"}, {"title": "Hotel Marhaba Club", "note": "1 025 avis", "address": "Boulevard 14 Janvier 2011, Sousse, Gouvernorat de Sousse, Tunisie"}, {"title": "Royal Kenz Hotel Thalasso & Spa", "note": "2 502 avis", "address": "Jin\u00e9ne El Kantaoui, Port El Kantaoui, Gouvernorat de Sousse, Tunisie"}, {"title": "Orient Palace Hotel", "note": "1 019 avis", "address": "Boulevard 14 Janvier, Sousse, Gouvernorat de Sousse, Tunisie"}, {"title": "Occidental Sousse Marhaba", "note": "1 464 avis", "address": "Boulevard 14 Janvier 2011, Sousse, Gouvernorat de Sousse, Tunisie"}, {"title": "TUI Blue Scheherazade", "note": "2 251 avis", "address": "Boulevard du 14 Janvier, Sousse, Gouvernorat de Sousse, Tunisie"}, {"title": "Sentido Bellevue Park", "note": "2 721 avis", "address": "Bp 344, Port El Kantaoui, Gouvernorat de Sousse, Tunisie"}, {"title": "Palmyra Aquapark Kantaoui", "note": "2 154 avis", "address": "Route Touristique Jinene, Port El Kantaoui, Gouvernorat de Sousse, Tunisie"}, {"title": "El Mouradi Port El Kantaoui", "note": "1 004 avis", "address": "Zone Touristiques Sousse, Port El Kantaoui, Gouvernorat de Sousse, Tunisie"}, {"title": "El Mouradi Club Selima", "note": "671 avis", "address": "Zone Touristique El Kantaoui, Port El Kantaoui, Gouvernorat de Sousse, Tunisie"}, {"title": "H\u00f4tel Riviera", "note": "2 066 avis", "address": "Bp 55, Port El Kantaoui, Gouvernorat de Sousse, Tunisie"}, {"title": "Jinene & Royal Jinene Hotels", "note": "576 avis", "address": "Sdht, Boulevard du 14 Janvier Route Touristique Sousse, Sousse, Gouvernorat de Sousse, Tunisie"}, {"title": "Miramar Pirate's Gate", "note": "258 avis", "address": "Route Dkhila, Monastir, Gouvernorat de Monastir, Tunisie"}, {"title": "Iberostar Selection Kantaoui Bay", "note": "2 347 avis", "address": "Jinant El Kantaoui Hammam Sousse, Port El Kantaoui, Gouvernorat de Sousse, Tunisie"}, {"title": "Houria Palace", "note": "801 avis", "address": "Route Touristique Port El Kantaoui, Port El Kantaoui, Gouvernorat de Sousse, Tunisie"}, {"title": "Villa du Souss", "note": "37 avis", "address": "Dr Fouk Jerf Temsia, Agadir, R\u00e9gion de Souss-Massa-Draa, Maroc"}, {"title": "Sousse City & Beach Hotel", "note": "109 avis", "address": "Boulevard De La Corniche, Sousse, Gouvernorat de Sousse, Tunisie"}, {"title": "SunConnect One Resort Monastir", "note": "2 306 avis", "address": "Route Touristique TN., Monastir, Gouvernorat de Monastir, Tunisie"}, {"title": "JAZ Tour Khalef Thalasso & Spa", "note": "2 223 avis", "address": "Boulevard du 14 Janvier, Sousse, Gouvernorat de Sousse, Tunisie"}, {"title": "Sousse Pearl Marriott Resort & Spa", "note": "188 avis", "address": "Abdelhamid El Kadhi Avenue, Sousse, Gouvernorat de Sousse, Tunisie"}]