{"name": "Exquise Sousse", "rating": "3,3", "loc": "Avenue Khalifa El Karoui", "phone": "No Phone Given"}{"name": "P\u00e2tisserie Masmoudi- Khzema", "rating": "3,8", "loc": "Avenue la Perle du Sahel", "phone": "No Phone Given"}{"name": "Boulangerie & P\u00e2tisserie Flora", "rating": "4,2", "loc": "No Location Given", "phone": "No Phone Given"}{"name": "P\u00e2tisserie Pyramides", "rating": "3,3", "loc": "4051 Rue des Palmiers", "phone": "No Phone Given"}{"name": "P\u00e2tisserie r\u00e9gal", "rating": "3,4", "loc": "No Location Given", "phone": "No Phone Given"}{"name": "P\u00e2tisserie Cherif", "rating": "3,1", "loc": "Avenue la Perle du Sahel", "phone": "No Phone Given"}{"name": "P\u00e2tisserie Pascal", "rating": "4,5", "loc": "No Location Given", "phone": "No Phone Given"}{"name": "P\u00e2tisserie Mme Trabelsi", "rating": "4,4", "loc": "lotissement zarrouk khzema ouest", "phone": "No Phone Given"}{"name": "Gourmandise", "rating": "3,9", "loc": "Avenue Taieb Mehiri", "phone": "No Phone Given"}{"name": "P\u00e2tisserie Masmoudi- Sahloul", "rating": "3,4", "loc": "Avenue de Yasser Arafat", "phone": "No Phone Given"}{"name": "P\u00e2tisserie Mozart", "rating": "5,0", "loc": "Avenue Etawfeek", "phone": "No Phone Given"}{"name": "Boulangerie P\u00e2tisserie Savora", "rating": "3,7", "loc": "No Location Given", "phone": "No Phone Given"}{"name": "DECOGATO SOUSSE", "rating": "No Rating", "loc": "Avenue Hassen Ben Said Khezama ouest Sousse", "phone": "No Phone Given"}{"name": "Meilleur Go\u00fbt", "rating": "4,3", "loc": "Rue Abdelkader Ghariani", "phone": "No Phone Given"}{"name": "VIENNOISERIE L'ATELIER", "rating": "No Rating", "loc": "Ecole des Soeurs, Rue Bechir Sfar N\u00b02 \u00e0 c\u00f4t\u00e9 de l", "phone": "No Phone Given"}{"name": "P\u00e2tisserie H by Omar\u00ae- Sousse", "rating": "No Rating", "loc": "No Location Given", "phone": "No Phone Given"}{"name": "P\u00e2tisserie Tunisienne Chez Fathi Korchani", "rating": "5,0", "loc": "Rue de France", "phone": "No Phone Given"}{"name": "Mme Hazgui", "rating": "5,0", "loc": "37 Rue Panama, Sahloul 1 Sousse", "phone": "No Phone Given"}{"name": "L'Op\u00e9ra", "rating": "3,0", "loc": "Avenue Etawfeek", "phone": "No Phone Given"}